tiny_tree/_init__.py
tiny_tree/helpers.py
tiny_tree/to_rows.py
tiny_tree/to_tree.py
tiny_tree/util.py
tiny_tree-0.1.0.dist-info/LICENSE.txt
tiny_tree-0.1.0.dist-info/METADATA
tiny_tree-0.1.0.dist-info/WHEEL
tiny_tree-0.1.0.dist-info/top_level.txt
tiny_tree-0.1.0.dist-info/RECORD
