Metadata-Version: 2.1
Name: tiny-tree
Version: 0.1.0
Summary: 一个循环解决行转树的问题，快速，轻量，无依赖。
Home-page: https://github.com/zhengxs2018/tiny-tree
Author: zhengxs
Author-email: zhengxs2018@foxmail.com
Maintainer: zhengxs
Maintainer-email: zhengxs2018@foxmail.com
License: MIT
Project-URL: Source, https://github.com/zhengxs2018/tiny-tree/
Project-URL: Bug Tracker, https://github.com/zhengxs2018/tiny-tree/issues
Keywords: tree,array2tree,tree2array,array to tree,data-structures
Platform: UNKNOWN
Classifier: Topic :: Software Development
Classifier: Development Status :: 4 - Beta
Classifier: Intended Audience :: Developers
Classifier: Programming Language :: Python :: 3
Classifier: Programming Language :: Python :: 3.6
Classifier: Programming Language :: Python :: 3.7
Classifier: Programming Language :: Python :: 3.8
Classifier: Programming Language :: Python :: 3.9
Classifier: Programming Language :: Python :: 3 :: Only
Classifier: Operating System :: OS Independent
Classifier: License :: OSI Approved :: MIT License
Requires-Python: >=3.6
License-File: LICENSE.txt
